py_peak_splitting/__init__.py
py_peak_splitting/hampel_filter.py
py_peak_splitting/simulate_ps_signals.py
py_peak_splitting/th_filter.py
py_peak_splitting-0.0.2.dist-info/LICENCE
py_peak_splitting-0.0.2.dist-info/LICENSE.txt
py_peak_splitting-0.0.2.dist-info/METADATA
py_peak_splitting-0.0.2.dist-info/WHEEL
py_peak_splitting-0.0.2.dist-info/top_level.txt
py_peak_splitting-0.0.2.dist-info/RECORD
