Metadata-Version: 2.1
Name: py-peak-splitting
Version: 0.0.2
Summary: Utilities to de-noise time series from random telegraph noise / peak splitting artefacts
Home-page: https://github.com/OWI-Lab/py_peak_splitting
Author: D.J.M. Fallais
Author-email: dominik.fallais@vub.be
License: Creative Commons BY-SA 4.0
Keywords: engineering,peak-splitting,RTN,hampel,threshold
Platform: UNKNOWN
Classifier: Development Status :: 4 - Beta
Classifier: Intended Audience :: Science/Research
Classifier: Programming Language :: Python :: 3
Classifier: Programming Language :: Python :: 3.6
Classifier: Programming Language :: Python :: 3.7
License-File: LICENCE
License-File: LICENSE.txt
Requires-Dist: numpy
Requires-Dist: matplotlib
Requires-Dist: plotly
Requires-Dist: sklearn
